ibroadcastaio/__init__.py
ibroadcastaio/client.py
ibroadcastaio/const.py
ibroadcastaio-0.4.0.dist-info/METADATA
ibroadcastaio-0.4.0.dist-info/WHEEL
ibroadcastaio-0.4.0.dist-info/entry_points.txt
ibroadcastaio-0.4.0.dist-info/RECORD
