Metadata-Version: 2.3
Name: ibroadcastaio
Version: 0.4.0
Summary: Client for async communication with the iBroadcast api.
License: MIT
Author: Rob Sonke
Author-email: rob@tigrou.nl
Requires-Python: >=3.11,<4.0
Classifier: License :: OSI Approved :: MIT License
Classifier: Programming Language :: Python :: 3
Classifier: Programming Language :: Python :: 3.11
Classifier: Programming Language :: Python :: 3.12
Classifier: Programming Language :: Python :: 3.13
Requires-Dist: aiohttp (>=3.11.0,<4.0.0)
Requires-Dist: pre-commit (>=4.0.1,<5.0.0)
Requires-Dist: pylint (>=3.3.1,<4.0.0)
